{
  "name": "Jahziel Villasana-Espinoza",
  "info": {
    "label": "Software Engineer, Computer Science Undergrad",
    "brief": "Jahziel loves programming computers and solving deep technical problems. He has a special affinity for the Web, systems programming, all things Open Source, and standards maintenance and implementation. He also loves building community around software."
  },
  "contact": {
    "email": "jahz@gatech.edu",
    "phone": "(404)-428-7664"
  },
  "meta": {
    "version": "v1.0.1",
    "format": "FRESH@^1.0.0-beta",
    "modified": "2019-12-17T02:58:16.759Z",
    "url": "https://raw.githubusercontent.com/jsonresume/resume-schema/master/resume.json"
  },
  "location": {
    "city": "Duluth",
    "region": "Georgia",
    "country": "US",
    "code": "30096",
    "address": "4888 Duncan Wood Dr."
  },
  "employment": {
    "history": [
      {
        "position": "Software Engineering Intern",
        "employer": "State Farm",
        "summary": "Joined a small Enterprise Technology team that maintains several microservices and APIs for the Claims side of State Farm's business, using Spring, Node.js, and AWS.",
        "current": true,
        "start": "2019-05-13",
        "keywords": []
      },
      {
        "position": "Co-op Engineer",
        "employer": "Yokogawa Corp. of America",
        "summary": "",
        "start": "2017-08-20",
        "end": "2019-05-03",
        "keywords": [],
        "highlights": [
          "Developed .NET apps for a variety of departments with focus on streamlining and automating existing business processes",
          "Developed an Android app that streamlines plant tours, with estimated savings in engineering time of more than $10,000 per year"
        ]
      }
    ]
  },
  "education": {
    "level": "",
    "history": [
      {
        "institution": "Georgia Institute of Technology",
        "start": "2015-08-20",
        "end": "2020-12-14",
        "grade": "3.43",
        "curriculum": [
          "CS1332: Data Structures and Algorithms",
          "CS2110: Computer Organization and Programming: Assembly and C",
          "CS2200: Intro to Systems and Networking",
          "CS3210: Operating System Design",
          "CS4240: Compilers and Interpreters",
          "Capstone Project"
        ],
        "summary": "",
        "area": "Computer Science",
        "studyType": "B.S"
      }
    ]
  },
  "skills": {
    "sets": [
      {
        "name": "Programming Languages",
        "skills": [
          "JavaScript",
          "Go",
          "C",
          "Python",
          "C#",
          "Java"
        ]
      },
      {
        "name": "The Web!",
        "skills": [
          "Node.js",
          "React",
          "Redux",
          "Jekyll",
          "Flask",
          "HTML",
          "CSS"
        ]
      },
      {
        "name": "Source Control",
        "skills": [
          "Git",
          "GitHub"
        ]
      },
      {
        "name": "Databases",
        "skills": [
          "SQLite",
          "SQL Server",
          "DynamoDB"
        ]
      },
      {
        "name": "Linux/Unix",
        "skills": [
          "Ubuntu",
          "Bash",
          "vim"
        ]
      }
    ]
  },
  "social": [
    {
      "label": "Twitter",
      "network": "Twitter",
      "url": "https://twitter.com/jahz_v",
      "user": "jahz_v"
    },
    {
      "label": "Github",
      "network": "Github",
      "url": "https://github.com/jahzielv",
      "user": "jahzielv"
    }
  ],
  "interests": [
    {
      "name": "Web Standards",
      "keywords": [
        "ECMAScript",
        "documentation",
        "implemetation (browsers, engines)"
      ]
    },
    {
      "name": "Open Source",
      "keywords": [
        "maintenance",
        "culture",
        "community building"
      ]
    }
  ],
  "languages": [
    {
      "language": "English",
      "fluency": "Native speaker"
    },
    {
      "language": "Spanish",
      "fluency": "Native speaker"
    }
  ]
}